{
  "id": "guides/extensions",
  "title": "Extensions",
  "description": "Overview",
  "source": "@site/docs/guides/extensions.mdx",
  "sourceDirName": "guides",
  "slug": "/guides/extensions",
  "permalink": "/docs/guides/extensions",
  "draft": false,
  "unlisted": false,
  "tags": [],
  "version": "current",
  "sidebarPosition": 2,
  "frontMatter": {
    "title": "Extensions",
    "sidebar_position": 2
  },
  "sidebar": "tutorialSidebar",
  "previous": {
    "title": "Configuration",
    "permalink": "/docs/guides/configuration"
  },
  "next": {
    "title": "concepts",
    "permalink": "/docs/guides/concepts"
  }
}